doeloe/__init__.py
doeloe/converter.py
doeloe-0.0.1.dist-info/LICENSE
doeloe-0.0.1.dist-info/METADATA
doeloe-0.0.1.dist-info/WHEEL
doeloe-0.0.1.dist-info/top_level.txt
doeloe-0.0.1.dist-info/RECORD
