Metadata-Version: 2.1
Name: doeloe
Version: 0.0.1
Summary: A tool to convert old Indonesian language into EYD (Ejaan yang Disempurnakan)
Home-page: https://github.com/bookbot-hive/doeloe
Author: David Samuel
Author-email: davidsamuel.7878@gmail.com
License: Apache License
Platform: linux
Platform: unix
Platform: windows
License-File: LICENSE
